{
  "browserName": "chrome",
  "browserPath": "google-chrome",
  "browserVersion": "138.0.7204.157",
  "config": {
    "baseUrl": "http://lojaebac.ebaconline.art.br/",
    "projectRoot": "/home/runner/work/ebac-cypress-patterns/ebac-cypress-patterns",
    "projectName": "ebac-cypress-patterns",
    "configFile": "cypress.config.js",
    "isTextTerminal": true,
    "animationDistanceThreshold": 5,
    "arch": "x64",
    "blockHosts": null,
    "chromeWebSecurity": true,
    "clientCertificates": [],
    "defaultBrowser": null,
    "defaultCommandTimeout": 4000,
    "downloadsFolder": "/home/runner/work/ebac-cypress-patterns/ebac-cypress-patterns/cypress/downloads",
    "env": {
      "CACHE_FOLDER": "/home/runner/.cache/Cypress"
    },
    "execTimeout": 60000,
    "experimentalCspAllowList": false,
    "experimentalInteractiveRunEvents": false,
    "experimentalRunAllSpecs": false,
    "experimentalMemoryManagement": false,
    "experimentalModifyObstructiveThirdPartyCode": false,
    "injectDocumentDomain": false,
    "experimentalOriginDependencies": false,
    "experimentalSourceRewriting": false,
    "experimentalSingleTabRunMode": false,
    "experimentalStudio": false,
    "experimentalWebKitSupport": false,
    "fileServerFolder": "/home/runner/work/ebac-cypress-patterns/ebac-cypress-patterns",
    "fixturesFolder": "/home/runner/work/ebac-cypress-patterns/ebac-cypress-patterns/cypress/fixtures",
    "excludeSpecPattern": "*.hot-update.js",
    "includeShadowDom": false,
    "justInTimeCompile": true,
    "keystrokeDelay": 0,
    "modifyObstructiveCode": true,
    "numTestsKeptInMemory": 0,
    "platform": "linux",
    "pageLoadTimeout": 60000,
    "port": 41167,
    "projectId": null,
    "redirectionLimit": 20,
    "reporter": "spec",
    "reporterOptions": null,
    "requestTimeout": 5000,
    "resolvedNodePath": "/home/runner/actions-runner/cached/externals/node20/bin/node",
    "resolvedNodeVersion": "20.19.3",
    "responseTimeout": 30000,
    "retries": {
      "runMode": 0,
      "openMode": 0
    },
    "screenshotOnRunFailure": true,
    "screenshotsFolder": "/home/runner/work/ebac-cypress-patterns/ebac-cypress-patterns/cypress/screenshots",
    "slowTestThreshold": 10000,
    "scrollBehavior": "top",
    "supportFile": "/home/runner/work/ebac-cypress-patterns/ebac-cypress-patterns/cypress/support/e2e.js",
    "taskTimeout": 60000,
    "testIsolation": true,
    "trashAssetsBeforeRuns": true,
    "userAgent": null,
    "video": false,
    "videoCompression": false,
    "videosFolder": "/home/runner/work/ebac-cypress-patterns/ebac-cypress-patterns/cypress/videos",
    "viewportHeight": 660,
    "viewportWidth": 1000,
    "waitForAnimations": true,
    "watchForFileChanges": false,
    "specPattern": "cypress/e2e/**/*.cy.{js,jsx,ts,tsx}",
    "browsers": [
      {
        "channel": "stable",
        "displayName": "Chrome",
        "family": "chromium",
        "majorVersion": "138",
        "name": "chrome",
        "path": "google-chrome",
        "version": "138.0.7204.157"
      },
      {
        "channel": "stable",
        "displayName": "Chromium",
        "family": "chromium",
        "majorVersion": "138",
        "name": "chromium",
        "path": "chromium-browser",
        "version": "138.0.7204.0"
      },
      {
        "channel": "stable",
        "displayName": "Firefox",
        "family": "firefox",
        "majorVersion": "140",
        "name": "firefox",
        "path": "firefox",
        "version": "140.0.4"
      },
      {
        "channel": "stable",
        "displayName": "Edge",
        "family": "chromium",
        "majorVersion": "138",
        "name": "edge",
        "path": "microsoft-edge",
        "version": "138.0.3351.95"
      },
      {
        "channel": "stable",
        "displayName": "Electron",
        "family": "chromium",
        "majorVersion": 130,
        "name": "electron",
        "path": "",
        "version": "130.0.6723.137"
      }
    ],
    "cypressBinaryRoot": "/home/runner/.cache/Cypress/14.5.2/Cypress/resources/app",
    "hosts": null,
    "isInteractive": true,
    "version": "14.5.2",
    "testingType": "e2e",
    "browser": null,
    "cypressInternalEnv": "production"
  },
  "cypressVersion": "14.5.2",
  "endedTestsAt": "2025-07-23T20:12:48.758Z",
  "osName": "linux",
  "osVersion": "Ubuntu - ",
  "runs": [
    {
      "error": null,
      "reporter": "spec",
      "reporterStats": {
        "suites": 1,
        "tests": 2,
        "passes": 0,
        "pending": 0,
        "failures": 2,
        "start": "2025-07-23T20:12:02.214Z",
        "end": "2025-07-23T20:12:24.602Z",
        "duration": 22388
      },
      "screenshots": [
        {
          "height": 633,
          "name": null,
          "path": "/home/runner/work/ebac-cypress-patterns/ebac-cypress-patterns/cypress/screenshots/AppActions.cy.js/Teste de checkout -- Deve criar um novo endereço e efetuar uma compra (failed).png",
          "takenAt": "2025-07-23T20:12:17.220Z",
          "width": 1280
        },
        {
          "height": 633,
          "name": null,
          "path": "/home/runner/work/ebac-cypress-patterns/ebac-cypress-patterns/cypress/screenshots/AppActions.cy.js/Teste de checkout -- Deve efetuar uma compra com um endereço existente (failed).png",
          "takenAt": "2025-07-23T20:12:24.471Z",
          "width": 1280
        }
      ],
      "spec": {
        "absolute": "/home/runner/work/ebac-cypress-patterns/ebac-cypress-patterns/cypress/e2e/AppActions.cy.js",
        "fileExtension": ".js",
        "fileName": "AppActions",
        "name": "AppActions.cy.js",
        "relative": "cypress/e2e/AppActions.cy.js"
      },
      "stats": {
        "duration": 22392,
        "endedAt": "2025-07-23T20:12:24.601Z",
        "failures": 2,
        "passes": 0,
        "pending": 0,
        "skipped": 0,
        "startedAt": "2025-07-23T20:12:02.209Z",
        "suites": 1,
        "tests": 2
      },
      "tests": [
        {
          "attempts": [
            {
              "state": "failed"
            }
          ],
          "displayError": "AssertionError: Timed out retrying after 4000ms: Expected to find element: `[data-testid=\"addNewAddress\"]`, but never found it.\n    at Context.eval (webpack://ebac-cypress-patterns/./cypress/support/actions/addAddress.js:4:7)\n    at wrapped (http://lojaebac.ebaconline.art.br/__cypress/runner/cypress_runner.js:141524:43)",
          "duration": 15205,
          "state": "failed",
          "title": [
            "Teste de checkout",
            "Deve criar um novo endereço e efetuar uma compra"
          ]
        },
        {
          "attempts": [
            {
              "state": "failed"
            }
          ],
          "displayError": "AssertionError: Timed out retrying after 4000ms: Expected to find element: `[style=\"z-index: 0; display: flex;\"] > [style=\"background-color: rgb(242, 242, 242);\"] > :nth-child(1) > :nth-child(1) > :nth-child(1) > :nth-child(2) > :nth-child(1) > :nth-child(1) > :nth-child(1) > :nth-child(1) > [style=\"background-color: rgb(242, 242, 242); display: flex;\"] > :nth-child(1) > :nth-child(1) > .r-13awgt0 > :nth-child(3) > [data-testid=\"selectAddressOrContinueToPayment\"]`, but never found it.\n    at Context.eval (webpack://ebac-cypress-patterns/./cypress/support/actions/cart.js:15:5)\n    at wrapped (http://lojaebac.ebaconline.art.br/__cypress/runner/cypress_runner.js:141524:43)",
          "duration": 7123,
          "state": "failed",
          "title": [
            "Teste de checkout",
            "Deve efetuar uma compra com um endereço existente"
          ]
        }
      ],
      "video": null
    },
    {
      "error": null,
      "reporter": "spec",
      "reporterStats": {
        "suites": 1,
        "tests": 1,
        "passes": 0,
        "pending": 0,
        "failures": 1,
        "start": "2025-07-23T20:12:25.963Z",
        "end": "2025-07-23T20:12:39.182Z",
        "duration": 13219
      },
      "screenshots": [
        {
          "height": 633,
          "name": null,
          "path": "/home/runner/work/ebac-cypress-patterns/ebac-cypress-patterns/cypress/screenshots/intercept.cy.js/Teste de checkout -- Deve percorrer o fluxo de pesquisa e seleção e checkout de produtos (failed).png",
          "takenAt": "2025-07-23T20:12:39.069Z",
          "width": 1280
        }
      ],
      "spec": {
        "absolute": "/home/runner/work/ebac-cypress-patterns/ebac-cypress-patterns/cypress/e2e/intercept.cy.js",
        "fileExtension": ".js",
        "fileName": "intercept",
        "name": "intercept.cy.js",
        "relative": "cypress/e2e/intercept.cy.js"
      },
      "stats": {
        "duration": 13226,
        "endedAt": "2025-07-23T20:12:39.180Z",
        "failures": 1,
        "passes": 0,
        "pending": 0,
        "skipped": 0,
        "startedAt": "2025-07-23T20:12:25.954Z",
        "suites": 1,
        "tests": 1
      },
      "tests": [
        {
          "attempts": [
            {
              "state": "failed"
            }
          ],
          "displayError": "AssertionError: Timed out retrying after 4000ms: Expected to find element: `[data-testid=\"selectAddressOrContinueToPayment\"]`, but never found it.\n    at Context.eval (webpack://ebac-cypress-patterns/./cypress/support/actions/cart.js:31:5)\n    at wrapped (http://lojaebac.ebaconline.art.br/__cypress/runner/cypress_runner.js:141524:43)",
          "duration": 13195,
          "state": "failed",
          "title": [
            "Teste de checkout",
            "Deve percorrer o fluxo de pesquisa e seleção e checkout de produtos"
          ]
        }
      ],
      "video": null
    },
    {
      "error": null,
      "reporter": "spec",
      "reporterStats": {
        "suites": 1,
        "tests": 1,
        "passes": 1,
        "pending": 0,
        "failures": 0,
        "start": "2025-07-23T20:12:40.444Z",
        "end": "2025-07-23T20:12:48.759Z",
        "duration": 8315
      },
      "screenshots": [],
      "spec": {
        "absolute": "/home/runner/work/ebac-cypress-patterns/ebac-cypress-patterns/cypress/e2e/pageObjects.cy.js",
        "fileExtension": ".js",
        "fileName": "pageObjects",
        "name": "pageObjects.cy.js",
        "relative": "cypress/e2e/pageObjects.cy.js"
      },
      "stats": {
        "duration": 8318,
        "endedAt": "2025-07-23T20:12:48.758Z",
        "failures": 0,
        "passes": 1,
        "pending": 0,
        "skipped": 0,
        "startedAt": "2025-07-23T20:12:40.440Z",
        "suites": 1,
        "tests": 1
      },
      "tests": [
        {
          "attempts": [
            {
              "state": "passed"
            }
          ],
          "displayError": null,
          "duration": 8312,
          "state": "passed",
          "title": [
            "Teste de autenticação",
            "Deve autenticar o usuário"
          ]
        }
      ],
      "video": null
    }
  ],
  "startedTestsAt": "2025-07-23T20:12:02.209Z",
  "totalDuration": 43936,
  "totalFailed": 3,
  "totalPassed": 1,
  "totalPending": 0,
  "totalSkipped": 0,
  "totalSuites": 3,
  "totalTests": 4
}